Workbook

Sheet Summary
A1: Investor Summary — Path to a $10M+ Profitable Operation
A2: Camp Margaritaville RV Resort, Crystal Beach TX | $000s
A4: Metric | B4: 2026 (Base) | C4: 2027 (Y1) | D4: 2028 (Y2) | E4: 2029 (Y3)
A5: Total Revenue | B5: ='P&L (3-Year)'!B5 -> 9240 | C5: ='P&L (3-Year)'!C5 -> 11394 | D5: ='P&L (3-Year)'!D5 -> 15410 | E5: ='P&L (3-Year)'!E5 -> 18888
A6: EBITDA | B6: ='P&L (3-Year)'!B13 -> 3423 | C6: ='P&L (3-Year)'!C13 -> 4093 | D6: ='P&L (3-Year)'!D13 -> 5756 | E6: ='P&L (3-Year)'!E13 -> 7270
A7: EBITDA Margin % | B7: ='P&L (3-Year)'!B13/'P&L (3-Year)'!B5 -> 0.37045455 | C7: ='P&L (3-Year)'!C13/'P&L (3-Year)'!C5 -> 0.35922415 | D7: ='P&L (3-Year)'!D13/'P&L (3-Year)'!D5 -> 0.37352369 | E7: ='P&L (3-Year)'!E13/'P&L (3-Year)'!E5 -> 0.38490047
A8: Net Income (Pre-Tax) | B8: ='P&L (3-Year)'!B17 -> 1623 | C8: ='P&L (3-Year)'!C17 -> 2073 | D8: ='P&L (3-Year)'!D17 -> 2806 | E8: ='P&L (3-Year)'!E17 -> 3720
A10: Milestones
A11: • Revenue crosses $10M in Year 1 (2027) and reaches ~$18.9M by Year 3 (2029) — a ~27% CAGR.
A12: • EBITDA scales from ~$3.4M (2026) to ~$7.3M (2029); net pre-tax income roughly $1.6M to $3.7M.
A13: • Growth engines: 24 beach-house bungalows, +50 premium RV sites, a new event center, and a scaled Paradise Park concert series (8→16 shows).
A14: • ~$9.9M project capex funded by ~$7M senior debt + equity; new builds add ~$4.3M annual revenue by Year 3.
A15: • The License to Chill swim-up bar remains the margin engine; concert + event days multiply per-cap F&B spend.

Sheet Revenue Model
A1: Camp Margaritaville RV Resort — 3-Year Revenue Model
A2: Crystal Beach, TX | All figures in $000s | Prepared by the CFO Agent
A4: Revenue Stream | B4: 2026 (Base) | C4: 2027 (Y1) | D4: 2028 (Y2) | E4: 2029 (Y3) | F4: CAGR
A5: LODGING
A6: RV Sites (existing 204) | B6: 3600 | C6: 3816 | D6: 3969 | E6: 4088 | F6: =IF(B6=0,"",(E6/B6)^(1/3)-1) -> 0.043284597
A7: RV Premium Expansion (+50 sites) | B7: 0 | C7: 0 | D7: 480 | E7: 893 | F7: =IF(B7=0,"",(E7/B7)^(1/3)-1)
A8: Vacation Cabins (existing) | B8: 1250 | C8: 1313 | D8: 1366 | E8: 1407 | F8: =IF(B8=0,"",(E8/B8)^(1/3)-1) -> 0.040226775
A9: Beach House Bungalows (24 units) | B9: 0 | C9: 420 | D9: 1350 | E9: 2050 | F9: =IF(B9=0,"",(E9/B9)^(1/3)-1)
A10: AMENITIES & ANCILLARY
A11: VIP Cabanas & Daybeds | B11: 520 | C11: 595 | D11: 655 | E11: 700 | F11: =IF(B11=0,"",(E11/B11)^(1/3)-1) -> 0.10415887
A12: Day Passes (Pool) | B12: 360 | C12: 400 | D12: 460 | E12: 500 | F12: =IF(B12=0,"",(E12/B12)^(1/3)-1) -> 0.11572158
A13: Golf Carts & Camp Store | B13: 300 | C13: 360 | D13: 420 | E13: 470 | F13: =IF(B13=0,"",(E13/B13)^(1/3)-1) -> 0.16142776
A14: FOOD & BEVERAGE
A15: Fins Bar & Grill (Food) | B15: 1150 | C15: 1300 | D15: 1650 | E15: 1950 | F15: =IF(B15=0,"",(E15/B15)^(1/3)-1) -> 0.19246486
A16: License to Chill Bar (Beverage) | B16: 1500 | C16: 1750 | D16: 2150 | E16: 2550 | F16: =IF(B16=0,"",(E16/B16)^(1/3)-1) -> 0.19348319
A17: EVENTS
A18: Paradise Park Concert Series | B18: 560 | C18: 1440 | D18: 2160 | E18: 2880 | F18: =IF(B18=0,"",(E18/B18)^(1/3)-1) -> 0.72610875
A19: Event Center (Weddings / Corporate) | B19: 0 | C19: 0 | D19: 750 | E19: 1400 | F19: =IF(B19=0,"",(E19/B19)^(1/3)-1)
A20: TOTAL REVENUE | B20: =B6+B7+B8+B9+B11+B12+B13+B15+B16+B18+B19 -> 9240 | C20: =C6+C7+C8+C9+C11+C12+C13+C15+C16+C18+C19 -> 11394 | D20: =D6+D7+D8+D9+D11+D12+D13+D15+D16+D18+D19 -> 15410 | E20: =E6+E7+E8+E9+E11+E12+E13+E15+E16+E18+E19 -> 18888 | F20: =(E20/B20)^(1/3)-1 -> 0.26912578
A21: YoY Growth | C21: =C20/B20-1 -> 0.23311688 | D21: =D20/C20-1 -> 0.35246621 | E21: =E20/D20-1 -> 0.2256976
A23: Blue = input assumption · Black = formula. F&B rows feed the P&L. Concert series per Event Specialist agent.

Sheet P&L (3-Year)
A1: 3-Year P&L / EBITDA Bridge
A2: All figures in $000s | Costs are CFO-model inputs (see footnotes); subtotals & margins are formulas
B4: 2026 (Base) | C4: 2027 (Y1) | D4: 2028 (Y2) | E4: 2029 (Y3)
A5: Total Revenue | B5: ='Revenue Model'!B20 -> 9240 | C5: ='Revenue Model'!C20 -> 11394 | D5: ='Revenue Model'!D20 -> 15410 | E5: ='Revenue Model'!E20 -> 18888
A6: of which Food & Beverage | B6: ='Revenue Model'!B15+'Revenue Model'!B16 -> 2650 | C6: ='Revenue Model'!C15+'Revenue Model'!C16 -> 3050 | D6: ='Revenue Model'!D15+'Revenue Model'!D16 -> 3800 | E6: ='Revenue Model'!E15+'Revenue Model'!E16 -> 4500
A7: Food & Beverage COGS (28% of F&B) | B7: 742 | C7: 854 | D7: 1064 | E7: 1260
A8: Concert & Event Direct (talent+production) | B8: 270 | C8: 693 | D8: 1039 | E8: 1386
A9: GROSS PROFIT | B9: =B5-B7-B8 -> 8228 | C9: =C5-C7-C8 -> 9847 | D9: =D5-D7-D8 -> 13307 | E9: =E5-E7-E8 -> 16242
A10: Gross Margin % | B10: =B9/B5 -> 0.89047619 | C10: =C9/C5 -> 0.86422679 | D10: =D9/D5 -> 0.86353018 | E10: =E9/E5 -> 0.85991105
A11: Payroll & Benefits | B11: 2772 | C11: 3304 | D11: 4315 | E11: 5100
A12: Operating Expenses (util, mktg, ins, R&M, G&A, royalty) | B12: 2033 | C12: 2450 | D12: 3236 | E12: 3872
A13: EBITDA | B13: =B9-B11-B12 -> 3423 | C13: =C9-C11-C12 -> 4093 | D13: =D9-D11-D12 -> 5756 | E13: =E9-E11-E12 -> 7270
A14: EBITDA Margin % | B14: =B13/B5 -> 0.37045455 | C14: =C13/C5 -> 0.35922415 | D14: =D13/D5 -> 0.37352369 | E14: =E13/E5 -> 0.38490047
A15: Depreciation & Amortization | B15: 1100 | C15: 1300 | D15: 1900 | E15: 2400
A16: Interest Expense (expansion debt) | B16: 700 | C16: 720 | D16: 1050 | E16: 1150
A17: NET INCOME (Pre-Tax) | B17: =B13-B15-B16 -> 1623 | C17: =C13-C15-C16 -> 2073 | D17: =D13-D15-D16 -> 2806 | E17: =E13-E15-E16 -> 3720
A18: Net Margin % | B18: =B17/B5 -> 0.17564935 | C18: =C17/C5 -> 0.18193786 | D18: =D17/D5 -> 0.18208955 | E18: =E17/E5 -> 0.19695044
A20: Payroll ≈27-30% of revenue; Opex ≈20.5-22%; F&B COGS 28% of F&B rev; concert direct per Event Specialist (~$87K ticket-side/show).

Sheet Concert Series
A1: Paradise Park Concert Series — Talent & Economics
A2: Per Event Specialist Agent | Fees are PLANNING ESTIMATES pending agency quotes | 4,000 tickets/show, ~$45 blended
A4: Act (est. fee mid) | B4: Est. Fee | C4: Ticket Contrib. | D4: + Ancillary | E4: Total Contrib.
A5: Jimmy Buffett Tribute (A1A / Son of a Sailor) | B5: 13.75 | C5: =180-B5-50 -> 116.25 | D5: 61.6 | E5: =C5+D5 -> 177.85
A6: Bellamy Brothers | B6: 20 | C6: =180-B6-50 -> 110 | D6: 61.6 | E6: =C6+D6 -> 171.6
A7: Roger Creager | B7: 22.5 | C7: =180-B7-50 -> 107.5 | D7: 61.6 | E7: =C7+D7 -> 169.1
A8: Kevin Fowler | B8: 22.5 | C8: =180-B8-50 -> 107.5 | D8: 61.6 | E8: =C8+D8 -> 169.1
A9: Wade Bowen | B9: 30 | C9: =180-B9-50 -> 100 | D9: 61.6 | E9: =C9+D9 -> 161.6
A10: Josh Abbott Band | B10: 40 | C10: =180-B10-50 -> 90 | D10: 61.6 | E10: =C10+D10 -> 151.6
A11: Aaron Watson | B11: 40 | C11: =180-B11-50 -> 90 | D11: 61.6 | E11: =C11+D11 -> 151.6
A12: Yacht Rock Revue | B12: 42.5 | C12: =180-B12-50 -> 87.5 | D12: 61.6 | E12: =C12+D12 -> 149.1
A13: Casey Donahew Band | B13: 57.5 | C13: =180-B13-50 -> 72.5 | D13: 61.6 | E13: =C13+D13 -> 134.1
A14: Pat Green | B14: 57.5 | C14: =180-B14-50 -> 72.5 | D14: 61.6 | E14: =C14+D14 -> 134.1
A15: Note: all $ in $000s per show. Ticket contrib = $180 rev − fee − $50 variable (production+ticketing+mktg). Ancillary = 4,000 × $22 × 70%.
A17: Series Plan | B17: 2027 (Y1) | C17: 2028 (Y2) | D17: 2029 (Y3) | E17: 3-Yr
A18: Marquee Shows | B18: 8 | C18: 12 | D18: 16 | E18: =SUM(B18:D18) -> 36
A19: Ticket Revenue ($000s) | B19: =B18*180 -> 1440 | C19: =C18*180 -> 2160 | D19: =D18*180 -> 2880 | E19: =SUM(B19:D19) -> 6480
A20: Ancillary Revenue (gross, $000s) | B20: =B18*88 -> 704 | C20: =C18*88 -> 1056 | D20: =D18*88 -> 1408 | E20: =SUM(B20:D20) -> 3168
A21: Total Contribution ($000s) | B21: =B18*155 -> 1240 | C21: =C18*155 -> 1860 | D21: =D18*155 -> 2480 | E21: =SUM(B21:D21) -> 5580
A23: Blended ~$155K contribution/show (barbell of value/tribute acts + marquee names).

Sheet Expansion & Capex
A1: Expansion Projects & Capital Plan
A2: All figures in $000s
A4: Project | B4: Units | C4: Capex/Unit | D4: Total Capex | E4: Online | F4: Yr3 Revenue
A5: Beach House Bungalows | B5: 24 | C5: 185 | D5: =B5*C5 -> 4440 | E5: 2027-28 | F5: 2050
A6: RV Premium Expansion | B6: 50 | C6: 38 | D6: =B6*C6 -> 1900 | E6: 2028 | F6: 893
A7: Event Center | B7: 1 | C7: 3600 | D7: =B7*C7 -> 3600 | E7: 2028 | F7: 1400
A8: TOTAL | D8: =SUM(D5:D7) -> 9940 | F8: =SUM(F5:F7) -> 4343
A10: Funding
A11: Senior Debt (8%) | B11: 7000
A12: Equity / Cash | B12: =D8-B11 -> 2940
A13: New Annual Revenue by Yr3 | B13: =F8 -> 4343
A14: Simple Revenue/Capex (Yr3) | B14: =F8/D8 -> 0.43692153
A16: Bungalows phased 12 units 2027 + 12 units 2028. Capex/unit and funding split are planning assumptions.
